edl.py
edl_mod-0.0.40.dist-info/LICENSE
edl_mod-0.0.40.dist-info/METADATA
edl_mod-0.0.40.dist-info/WHEEL
edl_mod-0.0.40.dist-info/top_level.txt
edl_mod-0.0.40.dist-info/RECORD
