Metadata-Version: 2.1
Name: edl-mod
Version: 0.0.40
Summary: Module for editting and searching external dynamic lists (EDLs)
Home-page: https://github.com/ejohnfel/edl
Author: Eric Johnfelt
Author-email: ejohnfel@hotmail.com
Project-URL: Bug Tracker, https://github.com/ejohnfel/edl/issues
Classifier: Programming Language :: Python :: 3
Classifier: License :: OSI Approved :: MIT License
Classifier: Operating System :: OS Independent
Requires-Python: >=3.0
License-File: LICENSE
Requires-Dist: py-helper-mod
